alphax/__init__.py
alphax/estimate.py
alphax/utils.py
alphax_anishpyan-0.0.1.dist-info/LICENSE
alphax_anishpyan-0.0.1.dist-info/METADATA
alphax_anishpyan-0.0.1.dist-info/WHEEL
alphax_anishpyan-0.0.1.dist-info/top_level.txt
alphax_anishpyan-0.0.1.dist-info/RECORD
